apollo3/__init__.py
apollo3/change_type.py
apollo3/client.py
apollo3/response/__init__.py
apollo3/response/assembly.py
apollo3/response/change.py
apollo3_client-0.4.2.dist-info/LICENSE
apollo3_client-0.4.2.dist-info/METADATA
apollo3_client-0.4.2.dist-info/WHEEL
apollo3_client-0.4.2.dist-info/RECORD
