Metadata-Version: 2.1
Name: apollo3-client
Version: 0.4.2
Summary: Apollo3 python client
License: Apache 2
Author: Shashank Budhanuru Ramaraju
Author-email: shashank.b.r.gowda45587@gmail.com
Requires-Python: >=3.9,<4.0
Classifier: License :: Other/Proprietary License
Classifier: Programming Language :: Python :: 3
Classifier: Programming Language :: Python :: 3.9
Classifier: Programming Language :: Python :: 3.10
Classifier: Programming Language :: Python :: 3.11
Classifier: Programming Language :: Python :: 3.12
Requires-Dist: requests (>=2.31.0,<3.0.0)
